foragerpy/__init__.py
foragerpy/client.py
foragerpy/utils.py
foragerpy-0.0.1.dist-info/WHEEL
foragerpy-0.0.1.dist-info/METADATA
foragerpy-0.0.1.dist-info/RECORD
